django_road/__init__.py
django_road/admin.py
django_road/apps.py
django_road/models.py
django_road/pagination.py
django_road/permissions.py
django_road/serializer_fields.py
django_road/tests.py
django_road/urls.py
django_road/views.py
django_road-0.3.dist-info/LICENSE
django_road-0.3.dist-info/METADATA
django_road-0.3.dist-info/WHEEL
django_road-0.3.dist-info/top_level.txt
django_road-0.3.dist-info/RECORD
