Metadata-Version: 2.1
Name: django-road
Version: 0.3
Summary: ROAD - REST ORM API for Django
Home-page: https://github.com/SiSol-Systems/django-road
Author: Thomas Uher
Author-email: thomas.uher@sisol-systems.com
License: The MIT License
Keywords: django,road,rest,api,orm
Platform: OS Independent
Classifier: Programming Language :: Python :: 3
Classifier: License :: OSI Approved :: MIT License
Classifier: Operating System :: OS Independent
Requires-Python: >=3.6
Requires-Dist: djangorestframework
Requires-Dist: markdown
Requires-Dist: django-filter
